odoo/addons/product_pricelist_supplierinfo/README.rst
odoo/addons/product_pricelist_supplierinfo/__init__.py
odoo/addons/product_pricelist_supplierinfo/__manifest__.py
odoo/addons/product_pricelist_supplierinfo/i18n/es.po
odoo/addons/product_pricelist_supplierinfo/i18n/product_pricelist_supplierinfo.pot
odoo/addons/product_pricelist_supplierinfo/models/__init__.py
odoo/addons/product_pricelist_supplierinfo/models/product_pricelist.py
odoo/addons/product_pricelist_supplierinfo/models/product_product.py
odoo/addons/product_pricelist_supplierinfo/models/product_template.py
odoo/addons/product_pricelist_supplierinfo/readme/CONFIGURE.rst
odoo/addons/product_pricelist_supplierinfo/readme/CONTRIBUTORS.rst
odoo/addons/product_pricelist_supplierinfo/readme/DESCRIPTION.rst
odoo/addons/product_pricelist_supplierinfo/readme/INSTALL.rst
odoo/addons/product_pricelist_supplierinfo/readme/ROADMAP.rst
odoo/addons/product_pricelist_supplierinfo/readme/USAGE.rst
odoo/addons/product_pricelist_supplierinfo/static/description/icon.png
odoo/addons/product_pricelist_supplierinfo/static/description/index.html
odoo/addons/product_pricelist_supplierinfo/tests/__init__.py
odoo/addons/product_pricelist_supplierinfo/tests/test_product_supplierinfo.py
odoo/addons/product_pricelist_supplierinfo/views/product_pricelist_item_views.xml
odoo11_addon_product_pricelist_supplierinfo-11.0.1.1.0.99.dev8.dist-info/METADATA
odoo11_addon_product_pricelist_supplierinfo-11.0.1.1.0.99.dev8.dist-info/WHEEL
odoo11_addon_product_pricelist_supplierinfo-11.0.1.1.0.99.dev8.dist-info/top_level.txt
odoo11_addon_product_pricelist_supplierinfo-11.0.1.1.0.99.dev8.dist-info/RECORD
